COPYING
MANIFEST.in
README.rst
setup.py
docs/Doxyfile
docs/Makefile
docs/acknowledgements.rst
docs/api.rst
docs/conf.py
docs/index.rst
docs/installation.rst
docs/license.rst
docs/readthedocs_requirements.txt
docs/theory.rst
docs/theory.tex
docs/usage.rst
pymuvr/__init__.py
pymuvr.egg-info/PKG-INFO
pymuvr.egg-info/SOURCES.txt
pymuvr.egg-info/dependency_links.txt
pymuvr.egg-info/not-zip-safe
pymuvr.egg-info/requires.txt
pymuvr.egg-info/top_level.txt
pymuvr/examples/benchmark_versus_spykeutils.py
pymuvr/native/__init__.py
pymuvr/native/include/convolved_spike_train.hpp
pymuvr/native/include/van_rossum_multiunit.hpp
pymuvr/native/src/convolved_spike_train.cpp
pymuvr/native/src/python_bindings.cpp
pymuvr/native/src/van_rossum_multiunit.cpp
pymuvr/native/test/test_distance.cpp
pymuvr/native/test/test_product.cpp
pymuvr/native/test/test_train.cpp
pymuvr/test/__init__.py
pymuvr/test/test_pymuvr.py