Metadata-Version: 1.1
Name: pymuvr
Version: 1.3.3
Summary: Multi-unit Van Rossum spike train metric
Home-page: https://github.com/epiasini/pymuvr
Author: Eugenio Piasini
Author-email: e.piasini@ucl.ac.uk
License: GPLv3+
Platform: UNKNOWN
Classifier: Development Status :: 5 - Production/Stable
Classifier: Intended Audience :: Science/Research
Classifier: Topic :: Scientific/Engineering
Classifier: License :: OSI Approved :: GNU General Public License v3 or later (GPLv3+)
Classifier: Programming Language :: Python :: Implementation :: CPython
Classifier: Programming Language :: Python :: 2.7
Classifier: Programming Language :: Python :: 3.2
Classifier: Programming Language :: Python :: 3.3
Classifier: Programming Language :: Python :: 3.4
